datahunters/__init__.py
datahunters/assets/__init__.py
datahunters/assets/webdrivers/__init__.py
datahunters/assets/webdrivers/downloader.py
datahunters/ecom/__init__.py
datahunters/ecom/common.py
datahunters/ecom/amazon/amz_crawler.py
datahunters/ecom/amazon/amz_crawler1.py
datahunters/ecom/shopstyle/__init__.py
datahunters/ecom/shopstyle/crawler_aws.py
datahunters/ecom/shopstyle/crawler_local.py
datahunters/ecom/shopstyle/scraper.py
datahunters/ecom/shopstyle/test_scraper.py
datahunters/ecom/shopstyle/extra/db_summary.py
datahunters/ecom/shopstyle/extra/test_docker.py
datahunters/ecom/shopstyle/extra/test_file_upload.py
datahunters/finance/__init__.py
datahunters/finance/alpaca/__init__.py
datahunters/finance/alpaca/api.py
datahunters/finance/robinhood/__init__.py
datahunters/finance/robinhood/api.py
datahunters/jobs/__init__.py
datahunters/movies/__init__.py
datahunters/movies/common.py
datahunters/movies/imdbapi/__init__.py
datahunters/movies/imdbapi/api.py
datahunters/movies/shared/__init__.py
datahunters/movies/tmdb/__init__.py
datahunters/movies/tmdb/api.py
datahunters/news/__init__.py
datahunters/news/base.py
datahunters/news/datanews/__init__.py
datahunters/news/datanews/api.py
datahunters/news/gnews/__init__.py
datahunters/news/gnews/api.py
datahunters/news/mediastack/__init__.py
datahunters/news/mediastack/api.py
datahunters/news/newsapi/__init__.py
datahunters/news/newsapi/api.py
datahunters/realestate/__init__.py
datahunters/realestate/base.py
datahunters/realestate/zillow/__init__.py
datahunters/realestate/zillow/api.py
datahunters/science/__init__.py
datahunters/science/arxiv/__init__.py
datahunters/science/arxiv/api.py
datahunters/search/__init__.py
datahunters/search/common.py
datahunters/search/bing/__init__.py
datahunters/search/bing/api.py
datahunters/search/google/__init__.py
datahunters/search/google/api.py
datahunters/search/google/sample.py
datahunters/shared/__init__.py
datahunters/shared/common.py
datahunters/shared/selenium_scraper.py
datahunters-0.2.1.dist-info/LICENSE
datahunters-0.2.1.dist-info/METADATA
datahunters-0.2.1.dist-info/WHEEL
datahunters-0.2.1.dist-info/top_level.txt
datahunters-0.2.1.dist-info/RECORD
